setup.py
beary/__init__.py
beary/colors.py
beary/terminal.py
beary.egg-info/PKG-INFO
beary.egg-info/SOURCES.txt
beary.egg-info/dependency_links.txt
beary.egg-info/requires.txt
beary.egg-info/top_level.txt
beary.egg-info/zip-safe