Metadata-Version: 1.0
Name: beary
Version: 0.0.1
Summary: 🐻 Terminal library on top of bearlibterminal.
Home-page: http://github.com/Yuffster/beary
Author: Michelle Steigerwalt
Author-email: msteigerwalt@gmail.com
License: UNKNOWN
Platform: UNKNOWN
